MANIFEST.in
README.rst
setup.py
miRMag.egg-info/PKG-INFO
miRMag.egg-info/SOURCES.txt
miRMag.egg-info/dependency_links.txt
miRMag.egg-info/requires.txt
miRMag.egg-info/top_level.txt
mirmag/__init__.py
mirmag/energy.py
mirmag/garna.py
mirmag/logger.py
mirmag/matrix.py
mirmag/mhmm.py
mirmag/mirna.py
mirmag/organism.py
mirmag/phmm.py
mirmag/rnafold.py
mirmag/stemloop.py
mirmag/target.py
mirmag/utils.py
mirmag/articles/1986. Freier et al., Improved free-energy parameters ... .pdf
mirmag/articles/1989. Jaeger et al., Improved predictions ... .pdf
mirmag/software/GArna
mirmag/software/GArna.exe