Metadata-Version: 2.1
Name: miRMag
Version: 1.0.5
Summary: Tools to process miRNA sequences, to predict them, and to explore their features.
Home-page: https://github.com/Repoxitory/miRMag
Author: Pavel Vorozheykin
Author-email: pavel.vorozheykin@gmail.com
